pybettor/__init__.py
pybettor/bet_calc.py
pybettor/bet_prob.py
pybettor/break_even.py
pybettor/clv_calc.py
pybettor/convert_odds.py
pybettor/edge_calc.py
pybettor/expected_value_calc.py
pybettor/fair_odds.py
pybettor/hfa_calc.py
pybettor/hold_calc.py
pybettor/implied_odds.py
pybettor/implied_prob.py
pybettor/kelly.py
pybettor/kelly_bet.py
pybettor/over_round.py
pybettor/parlay_calc.py
pybettor/true_implied_prob.py
pybettor/true_probability.py
pybettor-1.1.3.dist-info/LICENSE.txt
pybettor-1.1.3.dist-info/METADATA
pybettor-1.1.3.dist-info/WHEEL
pybettor-1.1.3.dist-info/top_level.txt
pybettor-1.1.3.dist-info/RECORD
