Metadata-Version: 2.1
Name: pybettor
Version: 1.1.3
Summary: automates simple bettor tasks
Home-page: https://github.com/ian-shepherd/pybettor
Author: Ian Shepherd, Jason Lee, Jared Lee
Author-email: ian.shepherd123@gmail.com, jason@aisportsfirm.com, 13jaredlee@gmail.com
License: UNKNOWN
Platform: UNKNOWN
Classifier: Programming Language :: Python :: 3
Classifier: License :: OSI Approved :: MIT License
Classifier: Operating System :: OS Independent
License-File: LICENSE.txt
Requires-Dist: numpy
Requires-Dist: scipy
Requires-Dist: matplotlib
